tests/__init__.py
tests/app_test.py
tests/escape_test.py
tests/flux_test.py
tests/httputil_test.py
tests/jinja2_test.py
tests/log_test.py
tests/model_test.py
tests/runtests.py
tests/session_test.py
tests/util.py
tests/util_test.py
turbo/__init__.py
turbo/app.py
turbo/conf.py
turbo/flux.py
turbo/helper.py
turbo/httputil.py
turbo/log.py
turbo/model.py
turbo/mongo_model.py
turbo/register.py
turbo/session.py
turbo/template.py
turbo/util.py
turbo/core/__init__.py
turbo/core/exceptions.py
turbo/fake/__init__.py
turbo/fake/project_template/__init__.py
turbo/fake/project_template/app-server/__init__.py
turbo/fake/project_template/app-server/main.py
turbo/fake/project_template/app-server/setting.py
turbo/fake/project_template/app-server/apps/__init__.py
turbo/fake/project_template/app-server/apps/base.py
turbo/fake/project_template/app-server/apps/settings.py
turbo/fake/project_template/app-server/apps/app/__init__.py
turbo/fake/project_template/app-server/apps/app/api.py
turbo/fake/project_template/app-server/apps/app/app.py
turbo/fake/project_template/app-server/apps/app/base.py
turbo/fake/project_template/app-server/apps/app/setting.py
turbo/fake/project_template/config/__init__.py
turbo/fake/project_template/db/__init__.py
turbo/fake/project_template/db/mongo_conn.py
turbo/fake/project_template/db/mysql_conn.py
turbo/fake/project_template/db/setting.py
turbo/fake/project_template/helpers/__init__.py
turbo/fake/project_template/helpers/settings.py
turbo/fake/project_template/helpers/user/__init__.py
turbo/fake/project_template/helpers/user/user.py
turbo/fake/project_template/lib/__init__.py
turbo/fake/project_template/lib/session.py
turbo/fake/project_template/models/__init__.py
turbo/fake/project_template/models/base.py
turbo/fake/project_template/models/settings.py
turbo/fake/project_template/models/user/__init__.py
turbo/fake/project_template/models/user/base.py
turbo/fake/project_template/models/user/model.py
turbo/fake/project_template/models/user/setting.py
turbo-0.5.1.dist-info/LICENSE
turbo-0.5.1.dist-info/METADATA
turbo-0.5.1.dist-info/WHEEL
turbo-0.5.1.dist-info/top_level.txt
turbo-0.5.1.dist-info/RECORD
