Metadata-Version: 2.1
Name: turbo
Version: 0.5.1
Summary: turbo is a web framework for fast web development based in tornado, mongodb, redis
Home-page: http://github.com/wecatch/app-turbo
Author: Wecatch.me
Author-email: wecatch.me@gmail.com
License: http://www.apache.org/licenses/LICENSE-2.0
Keywords: web framework tornado mongodb
Platform: UNKNOWN
Classifier: License :: OSI Approved :: Apache Software License
Classifier: Programming Language :: Python :: 2.6
Classifier: Programming Language :: Python :: 2.7
Classifier: Programming Language :: Python :: 3.3
Classifier: Programming Language :: Python :: 3.4
Classifier: Programming Language :: Python :: 3.5
Classifier: Programming Language :: Python :: 3.6
Classifier: Programming Language :: Python :: 3.7
Requires-Dist: tornado (>=6.0.0)
